backlog_schema/__init__.py
backlog_schema/model.py
backlog_schema-0.1.1.dist-info/WHEEL
backlog_schema-0.1.1.dist-info/METADATA
backlog_schema-0.1.1.dist-info/RECORD
