Metadata-Version: 2.1
Name: backlog-schema
Version: 0.1.1
Summary: backlog.com の pydantic model
Home-page: https://github.com/nnashiki/backlog-schema
Author: Niten Nashiki
Author-email: n.nashiki.work@gmail.com
Requires-Python: >=3.8,<4.0
Classifier: Programming Language :: Python :: 3
Classifier: Programming Language :: Python :: 3.10
Classifier: Programming Language :: Python :: 3.8
Classifier: Programming Language :: Python :: 3.9
Project-URL: Repository, https://github.com/nnashiki/backlog-schema
